emailver/__init__.py
emailver/emailveri.py
emailver-0.1.0.dist-info/METADATA
emailver-0.1.0.dist-info/WHEEL
emailver-0.1.0.dist-info/RECORD
