Metadata-Version: 2.1
Name: emailver
Version: 0.1.0
Summary: 
Author: pratap.ratiya
Author-email: pratap.ratiya@crestdatasys.com
Requires-Python: >=3.10,<4.0
Classifier: Programming Language :: Python :: 3
Classifier: Programming Language :: Python :: 3.10
Classifier: Programming Language :: Python :: 3.11
Classifier: Programming Language :: Python :: 3.12
Requires-Dist: requests (>=2.31.0,<3.0.0)
